MANIFEST.in
README.md
setup.py
committees/__init__.py
committees/admin.py
committees/app_registry.py
committees/feeds.py
committees/forms.py
committees/managers.py
committees/models.py
committees/module_meta.py
committees/search_indexes.py
committees/urls.py
committees/views.py
committees/migrations/0001_initial.py
committees/migrations/__init__.py
committees/static/chosen/chosen-sprite.png
committees/static/chosen/chosen.css
committees/static/chosen/chosen.jquery.min.js
committees/templates/committees/add.html
committees/templates/committees/base.html
committees/templates/committees/delete.html
committees/templates/committees/detail.html
committees/templates/committees/edit-meta.html
committees/templates/committees/edit.html
committees/templates/committees/form.html
committees/templates/committees/meta.html
committees/templates/committees/nav.html
committees/templates/committees/officer-formset.html
committees/templates/committees/options.html
committees/templates/committees/search-form.html
committees/templates/committees/search-result.html
committees/templates/committees/search.html
committees/templates/committees/media/css/committees.css
committees/templates/search/indexes/committees/committee_text.txt
committees/templatetags/__init__.py
committees/templatetags/committee_tags.py
tendenci_committees.egg-info/PKG-INFO
tendenci_committees.egg-info/SOURCES.txt
tendenci_committees.egg-info/dependency_links.txt
tendenci_committees.egg-info/requires.txt
tendenci_committees.egg-info/top_level.txt